{
  "tripduration": 489,
  "starttime": "2019-12-01 10:19:58.4680",
  "stoptime": "2019-12-01 10:28:08.1110",
  "start station id": 3378,
  "start station name": "E 76 St & Park Ave",
  "start station latitude": 40.773763,
  "start station longitude": -73.96222088,
  "end station id": 3148,
  "end station name": "E 84 St & 1 Ave",
  "end station latitude": 40.77565541,
  "end station longitude": -73.95068615,
  "bikeid": 29352,
  "usertype": "Subscriber",
  "birth year": 1988,
  "gender": "female"
}