{
  "tripduration": 1732,
  "starttime": "2019-12-01 08:09:01.4250",
  "stoptime": "2019-12-01 08:37:53.6370",
  "start station id": 3152,
  "start station name": "3 Ave & E 71 St",
  "start station latitude": 40.76873687,
  "start station longitude": -73.96119945,
  "end station id": 473,
  "end station name": "Rivington St & Chrystie St",
  "end station latitude": 40.72110063,
  "end station longitude": -73.9919254,
  "bikeid": 40835,
  "usertype": "Subscriber",
  "birth year": 1962,
  "gender": "male"
}