{
  "tripduration": 1277,
  "starttime": "2019-12-01 15:44:06.4920",
  "stoptime": "2019-12-01 16:05:23.5160",
  "start station id": 3115,
  "start station name": "India St & Manhattan Ave",
  "start station latitude": 40.73232194,
  "start station longitude": -73.9550858,
  "end station id": 3241,
  "end station name": "Monroe St & Tompkins Ave",
  "end station latitude": 40.686203,
  "end station longitude": -73.944694,
  "bikeid": 40528,
  "usertype": "Subscriber",
  "birth year": 1981,
  "gender": "female"
}