{
  "tripduration": 670,
  "starttime": "2019-12-01 15:48:32.3710",
  "stoptime": "2019-12-01 15:59:43.1670",
  "start station id": 3537,
  "start station name": "Carlton Ave & Dean St",
  "start station latitude": 40.6809741,
  "start station longitude": -73.9710097,
  "end station id": 3304,
  "end station name": "6 Ave & 9 St",
  "end station latitude": 40.668127,
  "end station longitude": -73.98377641,
  "bikeid": 41389,
  "usertype": "Subscriber",
  "birth year": 1989,
  "gender": "female"
}