{
  "tripduration": 659,
  "starttime": "2019-12-01 09:33:41.3340",
  "stoptime": "2019-12-01 09:44:40.5530",
  "start station id": 410,
  "start station name": "Suffolk St & Stanton St",
  "start station latitude": 40.72066442,
  "start station longitude": -73.98517977,
  "end station id": 320,
  "end station name": "Leonard St & Church St",
  "end station latitude": 40.717571,
  "end station longitude": -74.005549,
  "bikeid": 31202,
  "usertype": "Subscriber",
  "birth year": 1982,
  "gender": "male"
}