{
  "tripduration": 352,
  "starttime": "2019-12-01 13:39:28.1700",
  "stoptime": "2019-12-01 13:45:21.1640",
  "start station id": 161,
  "start station name": "LaGuardia Pl & W 3 St",
  "start station latitude": 40.72917025,
  "start station longitude": -73.99810231,
  "end station id": 483,
  "end station name": "E 12 St & 3 Ave",
  "end station latitude": 40.73223272,
  "end station longitude": -73.98889957,
  "bikeid": 15074,
  "usertype": "Subscriber",
  "birth year": 1998,
  "gender": "female"
}