{
  "tripduration": 379,
  "starttime": "2019-12-01 10:41:25.6170",
  "stoptime": "2019-12-01 10:47:44.9980",
  "start station id": 3580,
  "start station name": "St Johns Pl & Washington Ave",
  "start station latitude": 40.6737236,
  "start station longitude": -73.9631611,
  "end station id": 3346,
  "end station name": "Berkeley Pl & 7 Ave",
  "end station latitude": 40.675146838709786,
  "end station longitude": -73.97523209452629,
  "bikeid": 21584,
  "usertype": "Subscriber",
  "birth year": 1961,
  "gender": "female"
}