{
  "tripduration": 328,
  "starttime": "2019-12-01 12:40:46.4430",
  "stoptime": "2019-12-01 12:46:14.8350",
  "start station id": 473,
  "start station name": "Rivington St & Chrystie St",
  "start station latitude": 40.72110063,
  "start station longitude": -73.9919254,
  "end station id": 302,
  "end station name": "Avenue D & E 3 St",
  "end station latitude": 40.72082834,
  "end station longitude": -73.97793172,
  "bikeid": 40399,
  "usertype": "Subscriber",
  "birth year": 1986,
  "gender": "male"
}